certbot_regru/__init__.py
certbot_regru/dns.py
certbot_regru/dns_test.py
certbot_regru-1.0.1.dist-info/DESCRIPTION.rst
certbot_regru-1.0.1.dist-info/METADATA
certbot_regru-1.0.1.dist-info/RECORD
certbot_regru-1.0.1.dist-info/WHEEL
certbot_regru-1.0.1.dist-info/entry_points.txt
certbot_regru-1.0.1.dist-info/metadata.json
certbot_regru-1.0.1.dist-info/top_level.txt
etc/letsencrypt/regru.ini
